python_fixturify_project/__init__.py
python_fixturify_project/exceptions.py
python_fixturify_project/path_utils.py
python_fixturify_project/project.py
python_fixturify_project/utils.py
python_fixturify_project-1.0.0.dist-info/LICENSE
python_fixturify_project-1.0.0.dist-info/WHEEL
python_fixturify_project-1.0.0.dist-info/METADATA
python_fixturify_project-1.0.0.dist-info/RECORD
