Metadata-Version: 2.1
Name: python-fixturify-project
Version: 1.0.0
Summary: Dynamic fixture creation for your tests
Home-page: https://github.com/scalvert/python-fixturify-project
License: MIT
Keywords: fixtures,dynamic fixtures,test fixtures
Author: python-fixturify-project
Author-email: steve.calvert@gmail.com
Requires-Python: >=3.8,<4.0
Classifier: Development Status :: 5 - Production/Stable
Classifier: Intended Audience :: Developers
Classifier: License :: OSI Approved :: MIT License
Classifier: Operating System :: OS Independent
Classifier: Programming Language :: Python :: 3
Classifier: Programming Language :: Python :: 3.8
Classifier: Programming Language :: Python :: 3.9
Classifier: Programming Language :: Python :: 3.10
Classifier: Programming Language :: Python :: 3.11
Classifier: Programming Language :: Python :: 3
Classifier: Programming Language :: Python :: 3.10
Classifier: Programming Language :: Python :: 3.7
Classifier: Programming Language :: Python :: 3.8
Classifier: Programming Language :: Python :: 3.9
Classifier: Topic :: Software Development :: Libraries :: Python Modules
Requires-Dist: deepdiff (>=5.8.1,<6.0.0)
Requires-Dist: dict-path (>=1.0.1,<2.0.0)
Requires-Dist: importlib_metadata (>=4.5.0,<5.0.0) ; python_version < "3.8"
Requires-Dist: wcmatch (>=8.4.1,<9.0.0)
Project-URL: Repository, https://github.com/scalvert/python-fixturify-project
